MyCode.cp311-win_amd64.pyd
Enumarator_Window-0.0.2.dist-info/METADATA
Enumarator_Window-0.0.2.dist-info/WHEEL
Enumarator_Window-0.0.2.dist-info/top_level.txt
Enumarator_Window-0.0.2.dist-info/RECORD
