Metadata-Version: 2.1
Name: Enumarator-Window
Version: 0.0.2
Summary: Example project using pybind11
Author: Sulthan Amanu
Author-email: sulthan4380@example.com
